syntaxmaker/__init__.py
syntaxmaker/adposition_tool.py
syntaxmaker/converter.py
syntaxmaker/grammar.json
syntaxmaker/head.py
syntaxmaker/inflector.py
syntaxmaker/locative_case.json
syntaxmaker/noun_tool.py
syntaxmaker/phrase.py
syntaxmaker/pronoun_tool.py
syntaxmaker/syntax_maker.py
syntaxmaker/ud_map.json
syntaxmaker/verb_valence.py
syntaxmaker/verb_valences_new.json
syntaxmaker/data/postpositions.csv
syntaxmaker/data/prepositions.csv
syntaxmaker-2.0.1.dist-info/METADATA
syntaxmaker-2.0.1.dist-info/RECORD
syntaxmaker-2.0.1.dist-info/WHEEL
syntaxmaker-2.0.1.dist-info/top_level.txt
