Metadata-Version: 2.1
Name: syntaxmaker
Version: 2.0.1
Summary: The NLG tool for Finnish
Home-page: https://github.com/mikahama/syntaxmaker/
Author: Mika Hämäläinen, University of Helsinki
Author-email: mika.hamalainen@helsinki.fi
License: Apache License, Version 2.0
Keywords: NLG Finnish
Platform: UNKNOWN
Classifier: Development Status :: 5 - Production/Stable
Classifier: Intended Audience :: Developers
Classifier: Topic :: Text Processing
Classifier: Natural Language :: Finnish
Classifier: Programming Language :: Python :: 3
Requires-Dist: uralicNLP (>=1.2.2)
